<annotation>
	<folder>sample1</folder>
	<filename>60890246-cac2-11ee-b836-2f1755a15416.jpg</filename>
	<path>/home/gupengxi/Documents/AirHokey-Robot/vision/data/images/sample1/60890246-cac2-11ee-b836-2f1755a15416.jpg</path>
	<source>
		<database>Unknown</database>
	</source>
	<size>
		<width>1920</width>
		<height>1080</height>
		<depth>3</depth>
	</size>
	<segmented>0</segmented>
	<object>
		<name>player</name>
		<pose>Unspecified</pose>
		<truncated>0</truncated>
		<difficult>0</difficult>
		<bndbox>
			<xmin>403</xmin>
			<ymin>471</ymin>
			<xmax>549</xmax>
			<ymax>620</ymax>
		</bndbox>
	</object>
	<object>
		<name>player</name>
		<pose>Unspecified</pose>
		<truncated>0</truncated>
		<difficult>0</difficult>
		<bndbox>
			<xmin>1319</xmin>
			<ymin>686</ymin>
			<xmax>1475</xmax>
			<ymax>831</ymax>
		</bndbox>
	</object>
	<object>
		<name>puck</name>
		<pose>Unspecified</pose>
		<truncated>0</truncated>
		<difficult>0</difficult>
		<bndbox>
			<xmin>1008</xmin>
			<ymin>749</ymin>
			<xmax>1118</xmax>
			<ymax>867</ymax>
		</bndbox>
	</object>
	<object>
		<name>table</name>
		<pose>Unspecified</pose>
		<truncated>0</truncated>
		<difficult>0</difficult>
		<bndbox>
			<xmin>245</xmin>
			<ymin>153</ymin>
			<xmax>1596</xmax>
			<ymax>919</ymax>
		</bndbox>
	</object>
</annotation>
